Metadata-Version: 2.1
Name: python-flipkart-scraper
Version: 1.0.0
Summary: Scrap Product Data from Flipkart
Home-page: https://github.com/sannjayy/python_flipkart_scraper
Author: Sanjay Sikdar
Author-email: me@sanjaysikdar.dev
License: MIT
Project-URL: Bug Reports, https://github.com/sannjayy/python_flipkart_scraper/issues
Project-URL: Funding, https://www.paypal.com/paypalme/znasofficial
Project-URL: Say Thanks!, https://saythanks.io/to/sannjayy
Project-URL: Source, https://github.com/sannjayy/python_flipkart_scraper/
Keywords: python,scraper,flipkart scraper
Classifier: Development Status :: 5 - Production/Stable
Classifier: Intended Audience :: Developers
Classifier: Topic :: Software Development :: Libraries :: Python Modules
Classifier: Operating System :: OS Independent
Classifier: License :: OSI Approved :: MIT License
Classifier: Programming Language :: Python :: 3.7
Classifier: Programming Language :: Python :: 3.8
Classifier: Programming Language :: Python :: 3.9
Classifier: Programming Language :: Python :: 3.10
Requires-Python: >=3.9, <4
License-File: LICENSE
